okschema/__init__.py
okschema/schema.py
okschema-0.2.dist-info/METADATA
okschema-0.2.dist-info/RECORD
okschema-0.2.dist-info/WHEEL
okschema-0.2.dist-info/top_level.txt
