Metadata-Version: 2.1
Name: okschema
Version: 0.2
Summary: Validate JSON data using a schema written in Python
Home-page: https://github.com/okcode-eu/okschema
Author: Krzysztof Stachlewski
Author-email: stach@stachlewski.info
License: BSD
Platform: UNKNOWN
Requires-Dist: pendulum
